{
  "date": "2025-12-22",
  "monitored": 30,
  "signals_detected": 5,
  "trades": [
    {
      "ticker": "CMCT",
      "surge_pct": 7.44,
      "volume_ratio": 1712.0,
      "detect_time_kst": "20:06",
      "detect_price": 3.9,
      "surge_score": 12737.0,
      "allocation_pct": 70,
      "buy_price": 4.05,
      "buy_time_kst": "20:07",
      "buy_time_utc": "11:07",
      "sell_price": 3.44,
      "sell_time_kst": "20:23",
      "sell_reason": "손절(-15.1%)",
      "shares": 128,
      "invested_krw": 699840,
      "return_krw": 594432,
      "pnl_krw": -105408,
      "pnl_pct": -15.06
    },
    {
      "ticker": "FJET",
      "surge_pct": 9.44,
      "volume_ratio": 1054.0,
      "detect_time_kst": "23:31",
      "detect_price": 8.23,
      "surge_score": 9950.0,
      "allocation_pct": 30,
      "buy_price": 8.66,
      "buy_time_kst": "23:32",
      "buy_time_utc": "14:32",
      "sell_price": 11.29,
      "sell_time_kst": "00:27",
      "sell_reason": "익절(+30.4%)",
      "shares": 25,
      "invested_krw": 292185,
      "return_krw": 381142,
      "pnl_krw": 88957,
      "pnl_pct": 30.45
    },
    {
      "ticker": "HXHX",
      "surge_pct": 29.94,
      "volume_ratio": 235.0,
      "detect_time_kst": "01:05",
      "detect_price": 1.04,
      "surge_score": 7036.0,
      "allocation_pct": 30,
      "buy_price": 0.99,
      "buy_time_kst": "01:06",
      "buy_time_utc": "16:06",
      "sell_price": 0.83,
      "sell_time_kst": "01:24",
      "sell_reason": "손절(-16.8%)",
      "shares": 223,
      "invested_krw": 298858,
      "return_krw": 248577,
      "pnl_krw": -50281,
      "pnl_pct": -16.82
    },
    {
      "ticker": "SIDU",
      "surge_pct": 5.04,
      "volume_ratio": 802.0,
      "detect_time_kst": "21:32",
      "detect_price": 1.46,
      "surge_score": 4042.0,
      "allocation_pct": 30,
      "buy_price": 1.47,
      "buy_time_kst": "21:33",
      "buy_time_utc": "12:33",
      "sell_price": 1.91,
      "sell_time_kst": "22:39",
      "sell_reason": "익절(+30.0%)",
      "shares": 151,
      "invested_krw": 299456,
      "return_krw": 389353,
      "pnl_krw": 89897,
      "pnl_pct": 30.02
    },
    {
      "ticker": "QBTS",
      "surge_pct": 5.51,
      "volume_ratio": 209.0,
      "detect_time_kst": "23:45",
      "detect_price": 29.85,
      "surge_score": 1152.0,
      "allocation_pct": 30,
      "buy_price": 29.95,
      "buy_time_kst": "23:46",
      "buy_time_utc": "14:46",
      "sell_price": 32.37,
      "sell_time_kst": "09:59",
      "sell_reason": "강제청산(장마감)",
      "shares": 7,
      "invested_krw": 283073,
      "return_krw": 305896,
      "pnl_krw": 22823,
      "pnl_pct": 8.06
    }
  ],
  "total_invested_krw": 1873412,
  "total_return_krw": 1919400,
  "total_pnl_krw": 45988,
  "total_pnl_pct": 2.45
}