{
  "date": "2026-02-12",
  "monitored": 30,
  "signals_detected": 3,
  "trades": [
    {
      "ticker": "JDZG",
      "surge_pct": 17.57,
      "volume_ratio": 659.0,
      "detect_time_kst": "22:01",
      "detect_price": 1.84,
      "surge_score": 11579.0,
      "allocation_pct": 70,
      "buy_price": 1.56,
      "buy_time_kst": "22:02",
      "buy_time_utc": "13:02",
      "sell_price": 2.05,
      "sell_time_kst": "22:26",
      "sell_reason": "익절(+31.2%)",
      "shares": 331,
      "invested_krw": 697980,
      "return_krw": 916042,
      "pnl_krw": 218062,
      "pnl_pct": 31.24
    },
    {
      "ticker": "FSLY",
      "surge_pct": 5.77,
      "volume_ratio": 1781.0,
      "detect_time_kst": "21:26",
      "detect_price": 13.93,
      "surge_score": 10276.0,
      "allocation_pct": 30,
      "buy_price": 13.69,
      "buy_time_kst": "21:27",
      "buy_time_utc": "12:27",
      "sell_price": 17.81,
      "sell_time_kst": "04:50",
      "sell_reason": "익절(+30.1%)",
      "shares": 16,
      "invested_krw": 295618,
      "return_krw": 384696,
      "pnl_krw": 89078,
      "pnl_pct": 30.13
    },
    {
      "ticker": "ZSL",
      "surge_pct": 6.13,
      "volume_ratio": 343.0,
      "detect_time_kst": "01:13",
      "detect_price": 2.42,
      "surge_score": 2103.0,
      "allocation_pct": 30,
      "buy_price": 2.47,
      "buy_time_kst": "01:14",
      "buy_time_utc": "16:14",
      "sell_price": 2.66,
      "sell_time_kst": "09:59",
      "sell_reason": "강제청산(장마감)",
      "shares": 89,
      "invested_krw": 297052,
      "return_krw": 319383,
      "pnl_krw": 22331,
      "pnl_pct": 7.52
    }
  ],
  "total_invested_krw": 1290650,
  "total_return_krw": 1620121,
  "total_pnl_krw": 329471,
  "total_pnl_pct": 25.53
}