{
  "date": "2026-01-28",
  "monitored": 30,
  "signals_detected": 6,
  "trades": [
    {
      "ticker": "FEED",
      "surge_pct": 15.08,
      "volume_ratio": 946.0,
      "detect_time_kst": "18:21",
      "detect_price": 1.45,
      "surge_score": 14266.0,
      "allocation_pct": 70,
      "buy_price": 1.37,
      "buy_time_kst": "18:22",
      "buy_time_utc": "09:22",
      "sell_price": 1.81,
      "sell_time_kst": "23:26",
      "sell_reason": "익절(+32.5%)",
      "shares": 379,
      "invested_krw": 698914,
      "return_krw": 926086,
      "pnl_krw": 227172,
      "pnl_pct": 32.5
    },
    {
      "ticker": "TIRX",
      "surge_pct": 18.73,
      "volume_ratio": 393.0,
      "detect_time_kst": "03:49",
      "detect_price": 1.02,
      "surge_score": 7361.0,
      "allocation_pct": 30,
      "buy_price": 1.0,
      "buy_time_kst": "03:50",
      "buy_time_utc": "18:50",
      "sell_price": 1.31,
      "sell_time_kst": "05:26",
      "sell_reason": "익절(+30.6%)",
      "shares": 221,
      "invested_krw": 299663,
      "return_krw": 391286,
      "pnl_krw": 91623,
      "pnl_pct": 30.58
    },
    {
      "ticker": "TSLL",
      "surge_pct": 8.61,
      "volume_ratio": 518.0,
      "detect_time_kst": "06:07",
      "detect_price": 18.54,
      "surge_score": 4460.0,
      "allocation_pct": 30,
      "buy_price": 18.28,
      "buy_time_kst": "06:08",
      "buy_time_utc": "21:08",
      "sell_price": 17.9,
      "sell_time_kst": "09:59",
      "sell_reason": "강제청산(장마감)",
      "shares": 12,
      "invested_krw": 296200,
      "return_krw": 289980,
      "pnl_krw": -6220,
      "pnl_pct": -2.1
    },
    {
      "ticker": "PDYN",
      "surge_pct": 7.66,
      "volume_ratio": 397.0,
      "detect_time_kst": "21:19",
      "detect_price": 8.01,
      "surge_score": 3041.0,
      "allocation_pct": 30,
      "buy_price": 8.21,
      "buy_time_kst": "21:20",
      "buy_time_utc": "12:20",
      "sell_price": 7.23,
      "sell_time_kst": "09:59",
      "sell_reason": "강제청산(장마감)",
      "shares": 27,
      "invested_krw": 299109,
      "return_krw": 263534,
      "pnl_krw": -35575,
      "pnl_pct": -11.89
    }
  ],
  "total_invested_krw": 1593886,
  "total_return_krw": 1870886,
  "total_pnl_krw": 277000,
  "total_pnl_pct": 17.38
}